[
    {
      "_id": 762294436893,
      "name": "កំណត់ប្រដាប់ប្រដាផ្ទះបាយស៊ីលីកូនតូចចំនួន 12 គ្រឿងដែលបានកំណត់តាមវិធីផ្ទះបាយធ្វើពីឈើផ្ទះបាយដាក់ស្លាបព្រាធ្វើម្ហូបដាក់ឱ្យផលិតឧបករណ៍ផ្ទះបាយ",
      "price": {
        "minPrice": 10.57,
        "maxPrice": 10.57
      },
      "promoPrice": {
        "minPrice": 11.28,
        "maxPrice": 11.28
      },
      "stock": 0,
      "sold": 0,
      "mainImage": "https://g-search2.alicdn.com/img/bao/uploaded/i4/i3/2209852147344/O1CN01jvRaJC247bco3Y9ki_!!0-item_pic.jpg_180x180.jpg",
      "merchant": "馨蚕韵旗舰店",
      "provider": "taobao",
      "url": "http://detail.tmall.com/item.htm?id=600570643319"
    },
    {
      "_id": 671230977266,
      "name": " ស្លាបព្រានិងស្លាបព្រានៃគុយទាវអ៊ីតាលីដែលមានពណ៌ស្រស់ឆើតឆាយនៅលើទឹកហូរនីឡុងនីននិងគ្រឿងបន្លាស់គ្រឿងបន្លាស់ធ្វើម្ហូប",
      "price": {
        "minPrice": 4.15,
        "maxPrice": 4.15
      },
      "promoPrice": {
        "minPrice": 4.15,
        "maxPrice": 4.15
      },
      "stock": 0,
      "sold": 0,
      "mainImage": "https://g-search3.alicdn.com/img/bao/uploaded/i4/i1/2695631893/O1CN01PdAODr1Pr2V35CY4T_!!2695631893.jpg_180x180.jpg",
      "merchant": "紫丁香8259",
      "provider": "taobao",
      "url": "http://detail.tmall.com/item.htm?id=762294436893"
    },
    {
      "_id": 680175375969,
      "name": " បរិច្ចាគធ្នើផ្ទះបាយទំពក់ uok -hook -up ជញ្ជាំងជញ្ជាំង - ជញ្ជាំងដែលមានពន្លឺខ្ពស់ - ជញ្ជាំងផ្ទះបាយដែលមានវត្ថុបុរាណដែលមានរាងពងក្រពើដែលមានរាងពងក្រពើ",
      "price": {
        "minPrice": 2.48,
        "maxPrice": 2.48
      },
      "promoPrice": {
        "minPrice": 3.3,
        "maxPrice": 3.3
      },
      "stock": 1000,
      "sold": 1000,
      "mainImage": "https://g-search2.alicdn.com/img/bao/uploaded/i4/i1/2200724467829/O1CN01bSRDCK27hjZPK537o_!!0-item_pic.jpg_180x180.jpg",
      "merchant": "帅仕厨具旗舰店",
      "provider": "taobao",
      "url": "http://detail.tmall.com/item.htm?id=671230977266"
    },
    {
      "_id": 762430170547,
      "name": " ឧបករណ៍ផ្ទះបាយផ្ទះបាយផ្ទាល់ខ្លួនដាក់ដែកអ៊ីណុកដោះស្រាយសំភារៈផ្ទះបាយឈុតផ្ទះបាយ",
      "price": {
        "minPrice": 1.14,
        "maxPrice": 1.14
      },
      "promoPrice": {
        "minPrice": 1.3,
        "maxPrice": 1.3
      },
      "stock": 0,
      "sold": 0,
      "mainImage": "https://g-search3.alicdn.com/img/bao/uploaded/i4/i1/2209852147344/O1CN01nbIYx3247bcma8vgC_!!0-item_pic.jpg_180x180.jpg",
      "merchant": "馨蚕韵旗舰店",
      "provider": "taobao",
      "url": "http://detail.tmall.com/item.htm?id=680175375969"
    },
    {
      "_id": 724570259438,
      "name": " ឧបករណ៍ផ្ទះបាយដែកអ៊ីណុកដោះស្រាយដែកថែបស៊ីលីកូនឈុតផ្ទះបាយផ្ទះបាយផ្ទះបាយឧបករណ៍បំភ្លឺផ្ទះបាយធ្វើពីទំពាំងបាយជូរជ្រាបទឹក",
      "price": {
        "minPrice": 1.2,
        "maxPrice": 1.2
      },
      "promoPrice": {
        "minPrice": 1.07,
        "maxPrice": 1.07
      },
      "stock": 0,
      "sold": 0,
      "mainImage": "https://g-search3.alicdn.com/img/bao/uploaded/i4/i4/2206629141339/O1CN01dkyIzr1LlJBHdSTjR_!!0-item_pic.jpg_180x180.jpg",
      "merchant": "集博旗舰店",
      "provider": "taobao",
      "url": "http://detail.tmall.com/item.htm?id=762430170547"
    },
    {
      "_id": 696172643316,
      "name": " កុមារដែលជាគម្របប្រដាប់ក្មេងលេងផ្ទះបាយតូចមួយកាត់បន្លែនិងចំអិនម្ហូបនិងចុងភៅ",
      "price": {
        "minPrice": 1.65,
        "maxPrice": 1.65
      },
      "promoPrice": {
        "minPrice": 2.15,
        "maxPrice": 2.15
      },
      "stock": 2000,
      "sold": 2000,
      "mainImage": "https://g-search1.alicdn.com/img/bao/uploaded/i4/i4/2200829793397/O1CN01iFgJqY1axsF64dRoe_!!0-item_pic.jpg_180x180.jpg",
      "merchant": "途文母婴专营店",
      "provider": "taobao",
      "url": "http://detail.tmall.com/item.htm?id=724570259438"
    },
    {
      "_id": 755230646876,
      "name": " ជញ្ជាំងស៊ុមកាំបិតផ្ទះបាយ -Mounted -Funee ផ្ទះបាយពហុកាំបិតផ្ទុកកាំបិតដែលផ្ទុកកាំបិត chopstick បំពង់ដាក់ភ្ជាប់ប្រអប់តំឡើង",
      "price": {
        "minPrice": 2.65,
        "maxPrice": 2.65
      },
      "promoPrice": {
        "minPrice": 2.82,
        "maxPrice": 2.82
      },
      "stock": 800,
      "sold": 800,
      "mainImage": "https://g-search2.alicdn.com/img/bao/uploaded/i4/i2/2200778999140/O1CN01tbbj942HOAxJ7zNL7_!!0-item_pic.jpg_180x180.jpg",
      "merchant": "睦歌家居旗舰店",
      "provider": "taobao",
      "url": "http://detail.tmall.com/item.htm?id=696172643316"
    },
    {
      "_id": 716116179588,
      "name": " ប្រហាក់ប្រហែលនៃសេរ៉ាមិចសេរ៉ាមិចអារីសាពរប្រឆាំងនឹងម្សៅម្ទេសដុតដុតដុតនំស្លាបព្រាធ្វើម្ហូបផ្ទះបាយធ្វើម្ហូប",
      "price": {
        "minPrice": 32.41,
        "maxPrice": 32.41
      },
      "promoPrice": {
        "minPrice": 32.41,
        "maxPrice": 32.41
      },
      "stock": 0,
      "sold": 0,
      "mainImage": "https://g-search1.alicdn.com/img/bao/uploaded/i4/i3/377562020/O1CN012giQs61QnCmpfbOtE_!!377562020.jpg_180x180.jpg",
      "merchant": "tb20230307555",
      "provider": "taobao",
      "url": "http://detail.tmall.com/item.htm?id=755230646876"
    },
    {
      "_id": 13942016633,
      "name": " ការដឹកជញ្ជូនដែកអ៊ីណុករបស់ QP ដោយឥតគិតថ្លៃត្រីត្រីចៀនត្រីប៉ាក់ប៉ែលប៉ែលប៉ែលឧបករណ៍ធ្វើម្ហូបឧបករណ៍ផ្ទះបាយប្រដាប់ប្រដាផ្ទះបាយ",
      "price": {
        "minPrice": 8.33,
        "maxPrice": 8.33
      },
      "promoPrice": {
        "minPrice": 8.33,
        "maxPrice": 8.33
      },
      "stock": 0,
      "sold": 0,
      "mainImage": "https://g-search1.alicdn.com/img/bao/uploaded/i4/i4/TB1TTG0GFXXXXarXVXXXXXXXXXX_!!0-item_pic.jpg_180x180.jpg",
      "merchant": "莱珍斯旗舰店",
      "provider": "taobao",
      "url": "http://detail.tmall.com/item.htm?id=716116179588"
    },
    {
      "_id": 662952909346,
      "name": " ប្រហាក់ប្រហែលនៃសេរ៉ាមិចសេរ៉ាមិចអារីសាពរប្រឆាំងនឹងម្សៅម្ទេសដុតដុតដុតនំស្លាបព្រាធ្វើម្ហូបផ្ទះបាយធ្វើម្ហូប",
      "price": {
        "minPrice": 17.17,
        "maxPrice": 17.17
      },
      "promoPrice": {
        "minPrice": 18,
        "maxPrice": 18
      },
      "stock": 26,
      "sold": 26,
      "mainImage": "https://g-search2.alicdn.com/img/bao/uploaded/i4/i3/377562020/O1CN012giQs61QnCmpfbOtE_!!377562020.jpg_180x180.jpg",
      "merchant": "女儿谷",
      "provider": "taobao",
      "url": "http://detail.tmall.com/item.htm?id=13942016633"
    },
    {
      "_id": 665923704446,
      "name": " Hong Kong Hong Kong -Style Hong -Sthing No. 2 Spatula 10 2 ចុងភៅស្ពាន់ធ័រ 10 ពីរគ្រឿងពិសេសចៀនឈើធ្វើពីឈើអ៊ីណុក",
      "price": {
        "minPrice": 44.34,
        "maxPrice": 44.34
      },
      "promoPrice": {
        "minPrice": 53.01,
        "maxPrice": 53.01
      },
      "stock": 34,
      "sold": 34,
      "mainImage": "https://tbimg.zzqss.com/imgextra/i2/25804919/O1CN01bAnVP61mCx5NzEPs9_!!0-saturn_solar.jpg_180x180.jpg?x-oss-process=style/tbsy",
      "merchant": "老甘香港代购",
      "provider": "taobao",
      "url": "http://detail.tmall.com/item.htm?id=662952909346"
    },
    {
      "_id": 760090924461,
      "name": " ប្រហាក់ប្រហែលនៃសេរ៉ាមិចសេរ៉ាមិចអារីសាពរប្រឆាំងនឹងម្សៅម្ទេសដុតដុតដុតនំស្លាបព្រាធ្វើម្ហូបផ្ទះបាយធ្វើម្ហូប",
      "price": {
        "minPrice": 30.67,
        "maxPrice": 30.67
      },
      "promoPrice": {
        "minPrice": 30.67,
        "maxPrice": 30.67
      },
      "stock": 0,
      "sold": 0,
      "mainImage": "https://g-search3.alicdn.com/img/bao/uploaded/i4/O1CN01CQqUqp21Lr61BQ09k_!!2216757816969-0-picasso.jpg_180x180.jpg",
      "merchant": "阿萨直销店",
      "provider": "taobao",
      "url": "http://detail.tmall.com/item.htm?id=665923704446"
    },
    {
      "_id": 672844093343,
      "name": " ប្រអប់ផ្ទុកដែកអ៊ីណុកដែកអ៊ីណុកចង្កឹះផ្ទះបាយជញ្ជាំង - ការកាប់ចង្កឹះឧបករណ៍ផ្ទះឧបករណ៍ដើមចង្កឹះស្លាបព្រា",
      "price": {
        "minPrice": 2.88,
        "maxPrice": 2.88
      },
      "promoPrice": {
        "minPrice": 2.88,
        "maxPrice": 2.88
      },
      "stock": 2000,
      "sold": 2000,
      "mainImage": "https://g-search2.alicdn.com/img/bao/uploaded/i4/i4/2256715915/O1CN017zo1wj1tZ7TpjNO57_!!0-item_pic.jpg_180x180.jpg",
      "merchant": "帅仕官方旗舰店",
      "provider": "taobao",
      "url": "http://detail.tmall.com/item.htm?id=760090924461"
    },
    {
      "_id": 763073425756,
      "name": " ប្រហាក់ប្រហែលនៃសេរ៉ាមិចសេរ៉ាមិចអារីសាពរប្រឆាំងនឹងម្សៅម្ទេសដុតដុតដុតនំស្លាបព្រាធ្វើម្ហូបផ្ទះបាយធ្វើម្ហូប",
      "price": {
        "minPrice": 36.01,
        "maxPrice": 36.01
      },
      "promoPrice": {
        "minPrice": 36.01,
        "maxPrice": 36.01
      },
      "stock": 0,
      "sold": 0,
      "mainImage": "https://g-search3.alicdn.com/img/bao/uploaded/i4/i1/2216989584076/O1CN010HlMJY1fyrHVuQGHx_!!0-item_pic.jpg_180x180.jpg",
      "merchant": "园翌博嘉专卖店",
      "provider": "taobao",
      "url": "http://detail.tmall.com/item.htm?id=672844093343"
    },
    {
      "_id": 746904130129,
      "name": " New Sectic White Herbon PeramiCs CreamiCs AnamiS ប្រឆាំងនឹងអាន់ធ័រអាន់ឌែលកំពុងដុតប្រដាប់ប្រដាស្លាបព្រាស្លាបព្រាប្រដាប់ប្រដាក្មេងលេងធ្វើម្ហូប",
      "price": {
        "minPrice": 12.96,
        "maxPrice": 12.96
      },
      "promoPrice": {
        "minPrice": 12.96,
        "maxPrice": 12.96
      },
      "stock": 0,
      "sold": 0,
      "mainImage": "https://g-search1.alicdn.com/img/bao/uploaded/i4/i1/3090802586/O1CN01d7qWWY1UyR7XTeCIo_!!3090802586.jpg_180x180.jpg",
      "merchant": "桂花糕147",
      "provider": "taobao",
      "url": "http://detail.tmall.com/item.htm?id=763073425756"
    },
    {
      "_id": 682657150975,
      "name": " 304 កាំបិតកាំបិតដែកដែកអ៊ីណុកចំនួន 304 កន្លែងដាក់ជំរកទាំងអស់ -in -one y ចង្កឹះទ្រនាប់ទ្រនាប់នៃទ្រនាប់ដោយកាំបិត",
      "price": {
        "minPrice": 10.84,
        "maxPrice": 10.84
      },
      "promoPrice": {
        "minPrice": 11.5,
        "maxPrice": 11.5
      },
      "stock": 3,
      "sold": 3,
      "mainImage": "https://g-search3.alicdn.com/img/bao/uploaded/i4/i2/2213052485573/O1CN019VKCUU1r2U3DW1395_!!0-item_pic.jpg_180x180.jpg",
      "merchant": "圣狮居家日用旗舰店",
      "provider": "taobao",
      "url": "http://detail.tmall.com/item.htm?id=746904130129"
    },
    {
      "_id": 677937214549,
      "name": " អ្នកទេសចរអន្តោប្រវេសន៍ដែលមានចម្ងាយវាស់ស្ទង់វាស់ស្ទង់វាស់ស្ទង់ដែកអ៊ីណុករបស់ដែកអ៊ីណុកដែលមានរាងឡៃ 34 ",
      "price": {
        "minPrice": 0.48,
        "maxPrice": 0.48
      },
      "promoPrice": {
        "minPrice": 0.48,
        "maxPrice": 0.48
      },
      "stock": 1,
      "sold": 1,
      "mainImage": "https://g-search3.alicdn.com/img/bao/uploaded/i4/i1/247719383/O1CN01nWbiEE2JBT31rIOyv_!!247719383.jpg_180x180.jpg",
      "merchant": "hwfxianyu",
      "provider": "taobao",
      "url": "http://detail.tmall.com/item.htm?id=682657150975"
    },
    {
      "_id": 762859781554,
      "name": " ឧបករណ៍ចម្លាក់ដីឥដ្ឋចំនួន 14 ដុំចុចលើឧបករណ៍ភក់ដែលមានពណ៌ឆ្លាក់ស្រូបយកដីឥដ្ឋដីឥដ្ឋភក់ទឹកដីដីឥដ្ឋភក់",
      "price": {
        "minPrice": 4.02,
        "maxPrice": 4.02
      },
      "promoPrice": {
        "minPrice": 4.02,
        "maxPrice": 4.02
      },
      "stock": 0,
      "sold": 0,
      "mainImage": "https://g-search3.alicdn.com/img/bao/uploaded/i4/i4/2208782132519/O1CN012vY7GZ1UTkbkTAve1_!!2208782132519.jpg_180x180.jpg",
      "merchant": "英尼选品",
      "provider": "taobao",
      "url": "http://detail.tmall.com/item.htm?id=677937214549"
    },
    {
      "_id": 598926925768,
      "name": " ឧបករណ៍បំពងភក់ភក់ ប្រដាប់ប្រដាប្រើប្រាស់គ្រឿងម៉ាស៊ីនប្រដាប់ប្រដាប្រើប្រាស់គ្រឿងម៉ាស៊ីនប្រដាប់ប្រដាប្រើប្រាស់គ្រឿងម៉ាស៊ីនប្រពៃណីជាតិអ៊ីណុកហ្វីលហ្វីលហ្វីលអុឡិនប៉ែលដើម្បីចំអិនអំណោយស្លាបព្រា",
      "price": {
        "minPrice": 1.13,
        "maxPrice": 1.13
      },
      "promoPrice": {
        "minPrice": 1.48,
        "maxPrice": 1.48
      },
      "stock": 0,
      "sold": 0,
      "mainImage": "https://g-search1.alicdn.com/img/bao/uploaded/i4/i3/2201404524138/O1CN01FTuiQs1gRFSwRttl2_!!2201404524138.jpg_180x180.jpg",
      "merchant": "tb754644718",
      "provider": "taobao",
      "url": "http://detail.tmall.com/item.htm?id=762859781554"
    },
    {
      "_id": 755732601251,
      "name": " គុយទាវអ៊ីតាលីដែលមានពណ៌ស្រស់ឆើតឆាយតូចរបស់ជប៉ុនដែលមានពណ៌ស្រស់ឆើតឆាយ Nylon No-Ske-Kovel ធ្វើម្ហូបធ្វើម្ហូប",
      "price": {
        "minPrice": 5.81,
        "maxPrice": 5.81
      },
      "promoPrice": {
        "minPrice": 5.81,
        "maxPrice": 5.81
      },
      "stock": 0,
      "sold": 0,
      "mainImage": "https://g-search2.alicdn.com/img/bao/uploaded/i4/i3/2212026949212/O1CN016d9GIA2Hv9SveGfNT_!!0-item_pic.jpg_180x180.jpg",
      "merchant": "糯咪旗舰店",
      "provider": "taobao",
      "url": "http://detail.tmall.com/item.htm?id=598926925768"
    }
  ]